Workbook

Sheet 25% Promo
B1: PROMOTION ROI SCORECARD Spring Top Promo | Classic Crew Tee | Weeks 4-5 | 25 % off | Retail Price: $28.00 | Promo Price: $21.00
B5: Actual Units | D5: Baseline Units | F5: Gross Lift Units | H5: Cannibalization Units | J5: Net Lift Units | L5: Net Margin
B6: =Calcs1!B2 -> 89 | D6: =Calcs1!B3 -> 48.99 | F6: =Calcs1!B4 -> 40.01 | H6: =Calcs1!B5 -> 11.7 | J6: =Calcs1!B6 -> 28.31 | L6: =Calcs1!B7 -> -204.56

Sheet 15% Promo
B1: PROMOTION ROI SCORECARD Spring Top Promo | Classic Crew Tee | Weeks 5-6 | 15 % off | Retail Price: $28.00 | Promo Price: $23.80
B5: Actual Units | D5: Baseline Units | F5: Gross Lift Units | H5: Cannibalization Units | J5: Net Lift Units | L5: Net Margin
B6: =Calcs2!B2 -> 82 | D6: =Calcs2!B3 -> 46.67 | F6: =Calcs2!B4 -> 35.33 | H6: =Calcs2!B5 -> 1.8 | J6: =Calcs2!B6 -> 33.53 | L6: =Calcs2!B7 -> 115.46

Sheet Data1
A1: style_id | B1: week | C1: price | D1: retail | E1: discount_pct | F1: units_sold | G1: revenue | H1: is_promo_week | I1: role | J1: baseline_units | L1: promo_id | M1: PROMO_001 | O1: Component | P1: Amounts
A2: style_001 | B2: 1 | C2: 28 | D2: 28 | E2: 0 | F2: 29 | G2: 812 | H2: FALSE | I2: promoted | J2: 29.14 | L2: promo_name | M2: Spring Top Promo | O2: A. Incremental margin | P2: 355
A3: style_001 | B3: 2 | C3: 28 | D3: 28 | E3: 0 | F3: 29 | G3: 812 | H3: FALSE | I3: promoted | J3: 27.81 | L3: style_id | M3: style_001 | O3: B. Markdow Cost | P3: -343
A4: style_001 | B4: 3 | C4: 28 | D4: 28 | E4: 0 | F4: 25 | G4: 700 | H4: FALSE | I4: promoted | J4: 26.49 | L4: promo_weeks | M4: [4, 5] | O4: C. Cannib. Loss | P4: -216.56
A5: style_001 | B5: 4 | C5: 21 | D5: 28 | E5: 0.25 | F5: 44 | G5: 924 | H5: TRUE | I5: promoted | J5: 25.16 | L5: discount_pct | M5: 0.25 | O5: Net margin impact | P5: -204.56
A6: style_001 | B6: 5 | C6: 21 | D6: 28 | E6: 0.25 | F6: 45 | G6: 945 | H6: TRUE | I6: promoted | J6: 23.83 | L6: retail_price | M6: 28
A7: style_001 | B7: 6 | C7: 28 | D7: 28 | E7: 0 | F7: 21 | G7: 588 | H7: FALSE | I7: promoted | J7: 22.5 | L7: promo_price | M7: 21 | O7: Metric | P7: Value
A8: style_001 | B8: 7 | C8: 28 | D8: 28 | E8: 0 | F8: 22 | G8: 616 | H8: FALSE | I8: promoted | J8: 21.17 | L8: actual_units | M8: 89 | O8: Net margin | P8: -204.56
A9: style_001 | B9: 8 | C9: 28 | D9: 28 | E9: 0 | F9: 22 | G9: 616 | H9: FALSE | I9: promoted | J9: 19.84 | L9: baseline_units | M9: 49 | O9: ROI % | P9: -0.596
A10: style_001 | B10: 9 | C10: 28 | D10: 28 | E10: 0 | F10: 18 | G10: 504 | H10: FALSE | I10: promoted | J10: 18.51 | L10: gross_lift_units | M10: 40
A11: style_001 | B11: 10 | C11: 28 | D11: 28 | E11: 0 | F11: 18 | G11: 504 | H11: FALSE | I11: promoted | J11: 17.18 | L11: cannib_units | M11: 11.7
A12: style_001 | B12: 11 | C12: 28 | D12: 28 | E12: 0 | F12: 15 | G12: 420 | H12: FALSE | I12: promoted | J12: 15.85 | L12: net_lift_units | M12: 28.4
A13: style_001 | B13: 12 | C13: 28 | D13: 28 | E13: 0 | F13: 14 | G13: 392 | H13: FALSE | I13: promoted | J13: 14.52 | L13: cannib_rate_pct | M13: 29.1
A14: style_002 | B14: 1 | C14: 31.18 | D14: 31.18 | E14: 0 | F14: 19 | G14: 592.42 | H14: FALSE | I14: adjacent | J14: 19.46 | L14: cannib_flag | M14: ~
A15: style_002 | B15: 2 | C15: 31.18 | D15: 31.18 | E15: 0 | F15: 16 | G15: 498.88 | H15: FALSE | I15: adjacent | J15: 18.66
A16: style_002 | B16: 3 | C16: 31.18 | D16: 31.18 | E16: 0 | F16: 20 | G16: 623.6 | H16: FALSE | I16: adjacent | J16: 17.85
A17: style_002 | B17: 4 | C17: 31.18 | D17: 31.18 | E17: 0 | F17: 15 | G17: 467.7 | H17: TRUE | I17: adjacent | J17: 17.04
A18: style_002 | B18: 5 | C18: 31.18 | D18: 31.18 | E18: 0 | F18: 13 | G18: 405.34 | H18: TRUE | I18: adjacent | J18: 16.23
A19: style_002 | B19: 6 | C19: 31.18 | D19: 31.18 | E19: 0 | F19: 16 | G19: 498.88 | H19: FALSE | I19: adjacent | J19: 15.43
A20: style_002 | B20: 7 | C20: 31.18 | D20: 31.18 | E20: 0 | F20: 14 | G20: 436.52 | H20: FALSE | I20: adjacent | J20: 14.62
A21: style_002 | B21: 8 | C21: 31.18 | D21: 31.18 | E21: 0 | F21: 15 | G21: 467.7 | H21: FALSE | I21: adjacent | J21: 13.81
A22: style_002 | B22: 9 | C22: 31.18 | D22: 31.18 | E22: 0 | F22: 16 | G22: 498.88 | H22: FALSE | I22: adjacent | J22: 13
A23: style_002 | B23: 10 | C23: 31.18 | D23: 31.18 | E23: 0 | F23: 11 | G23: 342.98 | H23: FALSE | I23: adjacent | J23: 12.2
A24: style_002 | B24: 11 | C24: 31.18 | D24: 31.18 | E24: 0 | F24: 12 | G24: 374.16 | H24: FALSE | I24: adjacent | J24: 11.39
A25: style_002 | B25: 12 | C25: 31.18 | D25: 31.18 | E25: 0 | F25: 8 | G25: 249.44 | H25: FALSE | I25: adjacent | J25: 10.58
A26: style_003 | B26: 1 | C26: 26.4 | D26: 26.4 | E26: 0 | F26: 27 | G26: 712.8 | H26: FALSE | I26: adjacent | J26: 23.8
... A241: style_020 | B241: 12 | C241: 26.4 | D241: 26.4 | E241: 0 | F241: 5 | G241: 132 | H241: FALSE | I241: unrelated | J241: 5

Sheet Data2
A1: style_id | B1: week | C1: price | D1: retail | E1: discount_pct | F1: units_sold | G1: revenue | H1: is_promo_week | I1: role | J1: baseline_units | L1: promo_id | M1: PROMO_002
A2: style_001 | B2: 1 | C2: 28 | D2: 28 | E2: 0 | F2: 31 | G2: 868 | H2: FALSE | I2: promoted | J2: 28.35 | L2: promo_name | M2: Spring Top Promo â€” Revised Strategy
A3: style_001 | B3: 2 | C3: 28 | D3: 28 | E3: 0 | F3: 26 | G3: 728 | H3: FALSE | I3: promoted | J3: 27.23 | L3: style_id | M3: style_001
A4: style_001 | B4: 3 | C4: 28 | D4: 28 | E4: 0 | F4: 25 | G4: 700 | H4: FALSE | I4: promoted | J4: 26.12 | L4: promo_weeks | M4: [5, 6]
A5: style_001 | B5: 4 | C5: 28 | D5: 28 | E5: 0 | F5: 22 | G5: 616 | H5: FALSE | I5: promoted | J5: 25.01 | L5: discount_pct | M5: 0.15 | P5: Component | Q5: Amounts
A6: style_001 | B6: 5 | C6: 23.8 | D6: 28 | E6: 0.15 | F6: 47 | G6: 1118.6 | H6: TRUE | I6: promoted | J6: 23.89 | L6: retail_price | M6: 28 | P6: A. Incremental margin | Q6: 344.25
A7: style_001 | B7: 6 | C7: 23.8 | D7: 28 | E7: 0.15 | F7: 35 | G7: 833 | H7: TRUE | I7: promoted | J7: 22.78 | L7: promo_price | M7: 23.8 | P7: B. Markdown Cost | Q7: -196.14
A8: style_001 | B8: 7 | C8: 28 | D8: 28 | E8: 0 | F8: 23 | G8: 644 | H8: FALSE | I8: promoted | J8: 21.67 | L8: actual_units | M8: 82 | P8: C. Cannib. Loss | Q8: -32.65
A9: style_001 | B9: 8 | C9: 28 | D9: 28 | E9: 0 | F9: 21 | G9: 588 | H9: FALSE | I9: promoted | J9: 20.55 | L9: baseline_units | M9: 46.7 | P9: Net margin impact | Q9: 115.46
A10: style_001 | B10: 9 | C10: 28 | D10: 28 | E10: 0 | F10: 20 | G10: 560 | H10: FALSE | I10: promoted | J10: 19.44 | L10: gross_lift_units | M10: 35.3
A11: style_001 | B11: 10 | C11: 28 | D11: 28 | E11: 0 | F11: 22 | G11: 616 | H11: FALSE | I11: promoted | J11: 18.33 | L11: cannib_units | M11: 1.8 | P11: Metric | Q11: Value
A12: style_001 | B12: 11 | C12: 28 | D12: 28 | E12: 0 | F12: 17 | G12: 476 | H12: FALSE | I12: promoted | J12: 17.21 | L12: net_lift_units | M12: 22.5 | P12: Net margin | Q12: 115.46
A13: style_001 | B13: 12 | C13: 28 | D13: 28 | E13: 0 | F13: 13 | G13: 364 | H13: FALSE | I13: promoted | J13: 16.1 | L13: cannib_rate_pct | M13: 5 | P13: ROI % | Q13: 0.589
A14: style_002 | B14: 1 | C14: 27.51 | D14: 27.51 | E14: 0 | F14: 19 | G14: 522.69 | H14: FALSE | I14: adjacent | J14: 17.67 | L14: net_margin | M14: 115.46
A15: style_002 | B15: 2 | C15: 27.51 | D15: 27.51 | E15: 0 | F15: 16 | G15: 440.16 | H15: FALSE | I15: adjacent | J15: 17.06 | L15: roi_pct | M15: 58.9
A16: style_002 | B16: 3 | C16: 27.51 | D16: 27.51 | E16: 0 | F16: 17 | G16: 467.67 | H16: FALSE | I16: adjacent | J16: 16.46
A17: style_002 | B17: 4 | C17: 27.51 | D17: 27.51 | E17: 0 | F17: 15 | G17: 412.65 | H17: FALSE | I17: adjacent | J17: 15.85
A18: style_002 | B18: 5 | C18: 27.51 | D18: 27.51 | E18: 0 | F18: 13 | G18: 357.63 | H18: TRUE | I18: adjacent | J18: 15.24
A19: style_002 | B19: 6 | C19: 27.51 | D19: 27.51 | E19: 0 | F19: 13 | G19: 357.63 | H19: TRUE | I19: adjacent | J19: 14.63
A20: style_002 | B20: 7 | C20: 27.51 | D20: 27.51 | E20: 0 | F20: 14 | G20: 385.14 | H20: FALSE | I20: adjacent | J20: 14.02
A21: style_002 | B21: 8 | C21: 27.51 | D21: 27.51 | E21: 0 | F21: 12 | G21: 330.12 | H21: FALSE | I21: adjacent | J21: 13.41
A22: style_002 | B22: 9 | C22: 27.51 | D22: 27.51 | E22: 0 | F22: 12 | G22: 330.12 | H22: FALSE | I22: adjacent | J22: 12.8
A23: style_002 | B23: 10 | C23: 27.51 | D23: 27.51 | E23: 0 | F23: 14 | G23: 385.14 | H23: FALSE | I23: adjacent | J23: 12.19
A24: style_002 | B24: 11 | C24: 27.51 | D24: 27.51 | E24: 0 | F24: 14 | G24: 385.14 | H24: FALSE | I24: adjacent | J24: 11.58
A25: style_002 | B25: 12 | C25: 27.51 | D25: 27.51 | E25: 0 | F25: 9 | G25: 247.59 | H25: FALSE | I25: adjacent | J25: 10.97
A26: style_003 | B26: 1 | C26: 24.75 | D26: 24.75 | E26: 0 | F26: 25 | G26: 618.75 | H26: FALSE | I26: adjacent | J26: 24.22
A27: style_003 | B27: 2 | C27: 24.75 | D27: 24.75 | E27: 0 | F27: 23 | G27: 569.25 | H27: FALSE | I27: adjacent | J27: 23.21
... A241: style_020 | B241: 12 | C241: 47.12 | D241: 47.12 | E241: 0 | F241: 13 | G241: 612.56 | H241: FALSE | I241: unrelated | J241: 13

Sheet Calcs1
A1: Metric | B1: Value | D1: Week | E1: Actual Units | F1: Baseline Units | H1: Week | I1: Actual Units | J1: Baseline Units | L1: Component | M1: Amount
A2: Actual Units | B2: =SUMIFS(Table1[units_sold],Table1[style_id],"style_001",Table1[is_promo_week], TRUE) -> 89 | D2: 1 | E2: =SUMIFS(Table1[units_sold],Table1[style_id], "style_001",Table1[week], D2) -> 29 | F2: =SUMIFS(Table1[baseline_units],Table1[style_id], "style_001", Table1[week],D2) -> 29.14 | H2: 1 | I2: =SUMIFS(Table1[units_sold],Table1[role], "adjacent", Table1[week], H2) -> 87 | J2: =SUMIFS(Table1[baseline_units], Table1[role], "adjacent", Table1[week], H2) -> 84.08 | L2: A. Incremental Margin | M2: 355
A3: Baseline Units | B3: =SUMIFS(Table1[baseline_units],Table1[style_id], "style_001", Table1[is_promo_week], TRUE) -> 48.99 | D3: 2 | E3: =SUMIFS(Table1[units_sold],Table1[style_id], "style_001",Table1[week], D3) -> 29 | F3: =SUMIFS(Table1[baseline_units],Table1[style_id], "style_001", Table1[week],D3) -> 27.81 | H3: 2 | I3: =SUMIFS(Table1[units_sold],Table1[role], "adjacent", Table1[week], H3) -> 70 | J3: =SUMIFS(Table1[baseline_units], Table1[role], "adjacent", Table1[week], H3) -> 80.25 | L3: B. Markdown Cost | M3: -343
A4: Gross Lift | B4: =B2-B3 -> 40.01 | D4: 3 | E4: =SUMIFS(Table1[units_sold],Table1[style_id], "style_001",Table1[week], D4) -> 25 | F4: =SUMIFS(Table1[baseline_units],Table1[style_id], "style_001", Table1[week],D4) -> 26.49 | H4: 3 | I4: =SUMIFS(Table1[units_sold],Table1[role], "adjacent", Table1[week], H4) -> 82 | J4: =SUMIFS(Table1[baseline_units], Table1[role], "adjacent", Table1[week], H4) -> 76.42 | L4: C. Cannib. Loss | M4: -216.56
A5: Cannib. Units | B5: 11.7 | D5: 4 | E5: =SUMIFS(Table1[units_sold],Table1[style_id], "style_001",Table1[week], D5) -> 44 | F5: =SUMIFS(Table1[baseline_units],Table1[style_id], "style_001", Table1[week],D5) -> 25.16 | H5: 4 | I5: =SUMIFS(Table1[units_sold],Table1[role], "adjacent", Table1[week], H5) -> 67 | J5: =SUMIFS(Table1[baseline_units], Table1[role], "adjacent", Table1[week], H5) -> 72.6 | L5: Net Margin Impact | M5: -204.56
A6: Net Lift | B6: =B4-B5 -> 28.31 | D6: 5 | E6: =SUMIFS(Table1[units_sold],Table1[style_id], "style_001",Table1[week], D6) -> 45 | F6: =SUMIFS(Table1[baseline_units],Table1[style_id], "style_001", Table1[week],D6) -> 23.83 | H6: 5 | I6: =SUMIFS(Table1[units_sold],Table1[role], "adjacent", Table1[week], H6) -> 65 | J6: =SUMIFS(Table1[baseline_units], Table1[role], "adjacent", Table1[week], H6) -> 68.76
A7: Net Margin | B7: -204.56 | D7: 6 | E7: =SUMIFS(Table1[units_sold],Table1[style_id], "style_001",Table1[week], D7) -> 21 | F7: =SUMIFS(Table1[baseline_units],Table1[style_id], "style_001", Table1[week],D7) -> 22.5 | H7: 6 | I7: =SUMIFS(Table1[units_sold],Table1[role], "adjacent", Table1[week], H7) -> 62 | J7: =SUMIFS(Table1[baseline_units], Table1[role], "adjacent", Table1[week], H7) -> 64.95
A8: ROI % | B8: -0.596 | D8: 7 | E8: =SUMIFS(Table1[units_sold],Table1[style_id], "style_001",Table1[week], D8) -> 22 | F8: =SUMIFS(Table1[baseline_units],Table1[style_id], "style_001", Table1[week],D8) -> 21.17 | H8: 7 | I8: =SUMIFS(Table1[units_sold],Table1[role], "adjacent", Table1[week], H8) -> 60 | J8: =SUMIFS(Table1[baseline_units], Table1[role], "adjacent", Table1[week], H8) -> 61.11
D9: 8 | E9: =SUMIFS(Table1[units_sold],Table1[style_id], "style_001",Table1[week], D9) -> 22 | F9: =SUMIFS(Table1[baseline_units],Table1[style_id], "style_001", Table1[week],D9) -> 19.84 | H9: 8 | I9: =SUMIFS(Table1[units_sold],Table1[role], "adjacent", Table1[week], H9) -> 61 | J9: =SUMIFS(Table1[baseline_units], Table1[role], "adjacent", Table1[week], H9) -> 57.29
D10: 9 | E10: =SUMIFS(Table1[units_sold],Table1[style_id], "style_001",Table1[week], D10) -> 18 | F10: =SUMIFS(Table1[baseline_units],Table1[style_id], "style_001", Table1[week],D10) -> 18.51 | H10: 9 | I10: =SUMIFS(Table1[units_sold],Table1[role], "adjacent", Table1[week], H10) -> 63 | J10: =SUMIFS(Table1[baseline_units], Table1[role], "adjacent", Table1[week], H10) -> 53.46
D11: 10 | E11: =SUMIFS(Table1[units_sold],Table1[style_id], "style_001",Table1[week], D11) -> 18 | F11: =SUMIFS(Table1[baseline_units],Table1[style_id], "style_001", Table1[week],D11) -> 17.18 | H11: 10 | I11: =SUMIFS(Table1[units_sold],Table1[role], "adjacent", Table1[week], H11) -> 50 | J11: =SUMIFS(Table1[baseline_units], Table1[role], "adjacent", Table1[week], H11) -> 49.64
D12: 11 | E12: =SUMIFS(Table1[units_sold],Table1[style_id], "style_001",Table1[week], D12) -> 15 | F12: =SUMIFS(Table1[baseline_units],Table1[style_id], "style_001", Table1[week],D12) -> 15.85 | H12: 11 | I12: =SUMIFS(Table1[units_sold],Table1[role], "adjacent", Table1[week], H12) -> 45 | J12: =SUMIFS(Table1[baseline_units], Table1[role], "adjacent", Table1[week], H12) -> 45.82
D13: 12 | E13: =SUMIFS(Table1[units_sold],Table1[style_id], "style_001",Table1[week], D13) -> 14 | F13: =SUMIFS(Table1[baseline_units],Table1[style_id], "style_001", Table1[week],D13) -> 14.52 | H13: 12 | I13: =SUMIFS(Table1[units_sold],Table1[role], "adjacent", Table1[week], H13) -> 35 | J13: =SUMIFS(Table1[baseline_units], Table1[role], "adjacent", Table1[week], H13) -> 41.99

Sheet Calcs2
A1: Metric | B1: Value | D1: Week | E1: Actual Units | F1: Baseline Units | H1: Week | I1: Actual Units | J1: Baseline Units | L1: Component | M1: Amount
A2: Actual Units | B2: =SUMIFS(Table2[units_sold],Table2[style_id],"style_001",Table2[is_promo_week], TRUE) -> 82 | D2: 1 | E2: =SUMIFS(Table2[units_sold],Table2[style_id], "style_001",Table2[week], D2) -> 31 | F2: =SUMIFS(Table2[baseline_units],Table2[style_id], "style_001", Table2[week],D2) -> 28.35 | H2: 1 | I2: =SUMIFS(Table2[units_sold],Table2[role], "adjacent", Table2[week], H2) -> 90 | J2: =SUMIFS(Table2[baseline_units], Table2[role], "adjacent", Table2[week], H2) -> 85.75 | L2: A. Incremental Margin | M2: 355
A3: Baseline Units | B3: =SUMIFS(Table2[baseline_units],Table2[style_id], "style_001", Table2[is_promo_week], TRUE) -> 46.67 | D3: 2 | E3: =SUMIFS(Table2[units_sold],Table2[style_id], "style_001",Table2[week], D3) -> 26 | F3: =SUMIFS(Table2[baseline_units],Table2[style_id], "style_001", Table2[week],D3) -> 27.23 | H3: 2 | I3: =SUMIFS(Table2[units_sold],Table2[role], "adjacent", Table2[week], H3) -> 77 | J3: =SUMIFS(Table2[baseline_units], Table2[role], "adjacent", Table2[week], H3) -> 82.33 | L3: B. Markdown Cost | M3: -196.14
A4: Gross Lift | B4: =B2-B3 -> 35.33 | D4: 3 | E4: =SUMIFS(Table2[units_sold],Table2[style_id], "style_001",Table2[week], D4) -> 25 | F4: =SUMIFS(Table2[baseline_units],Table2[style_id], "style_001", Table2[week],D4) -> 26.12 | H4: 3 | I4: =SUMIFS(Table2[units_sold],Table2[role], "adjacent", Table2[week], H4) -> 83 | J4: =SUMIFS(Table2[baseline_units], Table2[role], "adjacent", Table2[week], H4) -> 78.93 | L4: C. Cannib. Loss | M4: -32.65
A5: Cannib. Units | B5: 1.8 | D5: 4 | E5: =SUMIFS(Table2[units_sold],Table2[style_id], "style_001",Table2[week], D5) -> 22 | F5: =SUMIFS(Table2[baseline_units],Table2[style_id], "style_001", Table2[week],D5) -> 25.01 | H5: 4 | I5: =SUMIFS(Table2[units_sold],Table2[role], "adjacent", Table2[week], H5) -> 70 | J5: =SUMIFS(Table2[baseline_units], Table2[role], "adjacent", Table2[week], H5) -> 75.52 | L5: Net Margin Impact | M5: 115.46
A6: Net Lift | B6: =B4-B5 -> 33.53 | D6: 5 | E6: =SUMIFS(Table2[units_sold],Table2[style_id], "style_001",Table2[week], D6) -> 47 | F6: =SUMIFS(Table2[baseline_units],Table2[style_id], "style_001", Table2[week],D6) -> 23.89 | H6: 5 | I6: =SUMIFS(Table2[units_sold],Table2[role], "adjacent", Table2[week], H6) -> 64 | J6: =SUMIFS(Table2[baseline_units], Table2[role], "adjacent", Table2[week], H6) -> 72.1
A7: Net Margin | B7: 115.46 | D7: 6 | E7: =SUMIFS(Table2[units_sold],Table2[style_id], "style_001",Table2[week], D7) -> 35 | F7: =SUMIFS(Table2[baseline_units],Table2[style_id], "style_001", Table2[week],D7) -> 22.78 | H7: 6 | I7: =SUMIFS(Table2[units_sold],Table2[role], "adjacent", Table2[week], H7) -> 64 | J7: =SUMIFS(Table2[baseline_units], Table2[role], "adjacent", Table2[week], H7) -> 68.69
A8: ROI % | B8: 0.589 | D8: 7 | E8: =SUMIFS(Table2[units_sold],Table2[style_id], "style_001",Table2[week], D8) -> 23 | F8: =SUMIFS(Table2[baseline_units],Table2[style_id], "style_001", Table2[week],D8) -> 21.67 | H8: 7 | I8: =SUMIFS(Table2[units_sold],Table2[role], "adjacent", Table2[week], H8) -> 62 | J8: =SUMIFS(Table2[baseline_units], Table2[role], "adjacent", Table2[week], H8) -> 65.28
D9: 8 | E9: =SUMIFS(Table2[units_sold],Table2[style_id], "style_001",Table2[week], D9) -> 21 | F9: =SUMIFS(Table2[baseline_units],Table2[style_id], "style_001", Table2[week],D9) -> 20.55 | H9: 8 | I9: =SUMIFS(Table2[units_sold],Table2[role], "adjacent", Table2[week], H9) -> 65 | J9: =SUMIFS(Table2[baseline_units], Table2[role], "adjacent", Table2[week], H9) -> 61.87
D10: 9 | E10: =SUMIFS(Table2[units_sold],Table2[style_id], "style_001",Table2[week], D10) -> 20 | F10: =SUMIFS(Table2[baseline_units],Table2[style_id], "style_001", Table2[week],D10) -> 19.44 | H10: 9 | I10: =SUMIFS(Table2[units_sold],Table2[role], "adjacent", Table2[week], H10) -> 62 | J10: =SUMIFS(Table2[baseline_units], Table2[role], "adjacent", Table2[week], H10) -> 58.45
D11: 10 | E11: =SUMIFS(Table2[units_sold],Table2[style_id], "style_001",Table2[week], D11) -> 22 | F11: =SUMIFS(Table2[baseline_units],Table2[style_id], "style_001", Table2[week],D11) -> 18.33 | H11: 10 | I11: =SUMIFS(Table2[units_sold],Table2[role], "adjacent", Table2[week], H11) -> 54 | J11: =SUMIFS(Table2[baseline_units], Table2[role], "adjacent", Table2[week], H11) -> 55.04
D12: 11 | E12: =SUMIFS(Table2[units_sold],Table2[style_id], "style_001",Table2[week], D12) -> 17 | F12: =SUMIFS(Table2[baseline_units],Table2[style_id], "style_001", Table2[week],D12) -> 17.21 | H12: 11 | I12: =SUMIFS(Table2[units_sold],Table2[role], "adjacent", Table2[week], H12) -> 61 | J12: =SUMIFS(Table2[baseline_units], Table2[role], "adjacent", Table2[week], H12) -> 51.63
D13: 12 | E13: =SUMIFS(Table2[units_sold],Table2[style_id], "style_001",Table2[week], D13) -> 13 | F13: =SUMIFS(Table2[baseline_units],Table2[style_id], "style_001", Table2[week],D13) -> 16.1 | H13: 12 | I13: =SUMIFS(Table2[units_sold],Table2[role], "adjacent", Table2[week], H13) -> 39 | J13: =SUMIFS(Table2[baseline_units], Table2[role], "adjacent", Table2[week], H13) -> 48.21
